Metadata-Version: 2.1
Name: codigofacilito-jorgef
Version: 0.0.1
Summary: este paquete de prueba, permite consumir el api de codigo facilito
Home-page: https://github.com/JorgeFigueroa/codigofacilito_package
Author: Jorge figueroa
Author-email: atientas0412@gmail.com
License: MIT
Keywords: codigofacilito_jorgef
Platform: UNKNOWN
Classifier: Development Status :: 3 - Alpha
Classifier: Intended Audience :: Developers
Classifier: Topic :: Software Development :: Build Tools
Classifier: License :: OSI Approved :: MIT License
Classifier: Programming Language :: Python :: 3
License-File: LICENSE.txt
